AUTHORS.rst
CONTRIBUTING.rst
HISTORY.rst
LICENSE
MANIFEST.in
README.rst
setup.cfg
setup.py
docs/Makefile
docs/authors.rst
docs/conf.py
docs/contributing.rst
docs/history.rst
docs/index.rst
docs/installation.rst
docs/make.bat
docs/readme.rst
docs/tutorial.rst
docs/usage.rst
docs/releases/v0.1.0.rst
poshsplice/__init__.py
poshsplice/consolidate_events.py
poshsplice/exons.py
poshsplice/generic.py
poshsplice/hmmscan.py
poshsplice/miso.py
poshsplice/splicestrength.py
poshsplice/transcribe.py
poshsplice/translate.py
poshsplice.egg-info/PKG-INFO
poshsplice.egg-info/SOURCES.txt
poshsplice.egg-info/dependency_links.txt
poshsplice.egg-info/not-zip-safe
poshsplice.egg-info/requires.txt
poshsplice.egg-info/top_level.txt
poshsplice/tests/__init__.py
poshsplice/tests/conftest.py
poshsplice/tests/hmmscan_out.txt
poshsplice/tests/test.bed
poshsplice/tests/test.chromsizes
poshsplice/tests/test.chromsizes~
poshsplice/tests/test.fasta
poshsplice/tests/test.fasta.fai
poshsplice/tests/test_hmmscan.py
poshsplice/tests/test_splicesitestrength.py