Metadata-Version: 1.1
Name: poshsplice
Version: 0.1.1
Summary: Poshsplice makes your splicing events fancy (posh) by annotating them!
Home-page: https://github.com/olgabot/poshsplice
Author: Olga Botvinnik
Author-email: olga.botvinnik@gmail.com
License: BSD
Keywords: poshsplice
Platform: UNKNOWN
Classifier: Development Status :: 2 - Pre-Alpha
Classifier: Intended Audience :: Developers
Classifier: License :: OSI Approved :: BSD License
Classifier: Natural Language :: English
Classifier: Programming Language :: Python :: 2
Classifier: Programming Language :: Python :: 2.6
Classifier: Programming Language :: Python :: 2.7
Classifier: Programming Language :: Python :: 3
Classifier: Programming Language :: Python :: 3.3
Classifier: Programming Language :: Python :: 3.4
